Metadata-Version: 2.4
Name: mhc-mlx
Version: 0.6.3
Summary: High-performance MLX implementation of Manifold-Constrained Hyper-Connections (mHC)
Author-email: Salvador Escobedo <svdrecbd@gmail.com>
License: MIT
Project-URL: Homepage, https://github.com/svdrecbd/mhc-mlx
Project-URL: Repository, https://github.com/svdrecbd/mhc-mlx
Project-URL: Issues, https://github.com/svdrecbd/mhc-mlx/issues
Classifier: Development Status :: 4 - Beta
Classifier: Intended Audience :: Developers
Classifier: Intended Audience :: Science/Research
Classifier: License :: OSI Approved :: MIT License
Classifier: Operating System :: MacOS :: MacOS X
Classifier: Operating System :: POSIX :: Linux
Classifier: Programming Language :: Python :: 3
Classifier: Programming Language :: Python :: 3.10
Classifier: Programming Language :: Python :: 3.11
Classifier: Programming Language :: Python :: 3.12
Classifier: Topic :: Scientific/Engineering :: Artificial Intelligence
Requires-Python: >=3.10
License-File: LICENSE
Requires-Dist: mlx>=0.30.0
Provides-Extra: dev
Requires-Dist: pytest>=7.4; extra == "dev"
Requires-Dist: build; extra == "dev"
Requires-Dist: twine; extra == "dev"
Requires-Dist: ruff; extra == "dev"
Provides-Extra: bench
Requires-Dist: matplotlib; extra == "bench"
Dynamic: license-file
